{
  "subreddit": "NotKenM",
  "url": "https://www.reddit.com/r/NotKenM",
  "meta": {
    "title": "Stuff that's not Ken M."
  },
  "posts": [
    {
      "title": "NotKenM on water supply",
      "permalink": "https://www.reddit.com/r/NotKenM/comments/1n17lbh/notkenm_on_water_supply/",
      "score": 18,
      "comments": 1,
      "post_id": "t3_1n17lbh",
      "post_type": "image",
      "domain": "i.redd.it",
      "author": "seaminator235",
      "author_id": "t2_3u45tebj",
      "subreddit_id": "t5_35lpq",
      "subreddit": "r/NotKenM",
      "created_ts": "2025-08-27T04:28:44.615000+0000",
      "content_href": "https://i.redd.it/0pigly67phlf1.jpeg",
      "content_preview": "",
      "flair": [],
      "thumbnail_url": "https://www.redditstatic.com/avatars/defaults/v2/avatar_default_7.png"
    },
    {
      "title": "Wireless PC's don't exist",
      "permalink": "https://www.reddit.com/r/NotKenM/comments/1mye055/wireless_pcs_dont_exist/",
      "score": 140,
      "comments": 2,
      "post_id": "t3_1mye055",
      "post_type": "crosspost",
      "domain": "i.redd.it",
      "author": "LazyAF786",
      "author_id": "t2_6puxl9e4",
      "subreddit_id": "t5_35lpq",
      "subreddit": "r/NotKenM",
      "created_ts": "2025-08-23T21:45:56.966000+0000",
      "content_href": "/r/confidentlyincorrect/comments/1mx5arq/wireless_pcs_dont_exist/",
      "content_preview": "",
      "flair": [],
      "thumbnail_url": "https://www.redditstatic.com/avatars/defaults/v2/avatar_default_4.png"
    },
    {
      "title": "Even said folks",
      "permalink": "https://www.reddit.com/r/NotKenM/comments/1mwxa41/even_said_folks/",
      "score": 363,
      "comments": 15,
      "post_id": "t3_1mwxa41",
      "post_type": "image",
      "domain": "i.imgur.com",
      "author": "cheeddubbisuh",
      "author_id": "t2_1uw586xmmj",
      "subreddit_id": "t5_35lpq",
      "subreddit": "r/NotKenM",
      "created_ts": "2025-08-22T04:46:44.082000+0000",
      "content_href": "https://i.imgur.com/DC5ruJY.png",
      "content_preview": "",
      "flair": [],
      "thumbnail_url": "https://external-preview.redd.it/even-said-folks-v0-Jdpb4JZU2cG0qguOhwn4SVLDO3ZKJIH36tJLHYPujcU.png?width=640&crop=smart&auto=webp&s=27a1671827bd4ea2f97708011fddff3b6f6258ee"
    },
    {
      "title": "Armed Buffalo",
      "permalink": "https://www.reddit.com/r/NotKenM/comments/1mnpn3p/armed_buffalo/",
      "score": 87,
      "comments": 2,
      "post_id": "t3_1mnpn3p",
      "post_type": "image",
      "domain": "i.redd.it",
      "author": "ChoixDansLaDate",
      "author_id": "t2_56okdtmk",
      "subreddit_id": "t5_35lpq",
      "subreddit": "r/NotKenM",
      "created_ts": "2025-08-11T21:22:43.877000+0000",
      "content_href": "https://i.redd.it/65xl2f0jjgif1.jpeg",
      "content_preview": "",
      "flair": [],
      "thumbnail_url": "https://preview.redd.it/armed-buffalo-v0-65xl2f0jjgif1.jpeg?width=640&crop=smart&auto=webp&s=87525d68c2e7f6e185828e42c0fccb262de599d0"
    },
    {
      "title": "NotKenM on weddings",
      "permalink": "https://www.reddit.com/r/NotKenM/comments/1mn8em7/notkenm_on_weddings/",
      "score": 206,
      "comments": 0,
      "post_id": "t3_1mn8em7",
      "post_type": "image",
      "domain": "i.redd.it",
      "author": "seqizz",
      "author_id": "t2_5d1yg",
      "subreddit_id": "t5_35lpq",
      "subreddit": "r/NotKenM",
      "created_ts": "2025-08-11T09:31:49.261000+0000",
      "content_href": "https://i.redd.it/2fftvl1l0dif1.jpeg",
      "content_preview": "",
      "flair": [],
      "thumbnail_url": "https://styles.redditmedia.com/t5_ddrsc/styles/profileIcon_3z65y5yfqkb01.jpg?width=64&height=64&frame=1&auto=webp&crop=64%3A64%2Csmart&s=ef9e98522e31d6e04a678ea8ac618c8507fcad48"
    },
    {
      "title": "No ma'am",
      "permalink": "https://www.reddit.com/r/NotKenM/comments/1mhjc2v/no_maam/",
      "score": 614,
      "comments": 1,
      "post_id": "t3_1mhjc2v",
      "post_type": "crosspost",
      "domain": "i.redd.it",
      "author": "uncle_hobo",
      "author_id": "t2_khpk5",
      "subreddit_id": "t5_35lpq",
      "subreddit": "r/NotKenM",
      "created_ts": "2025-08-04T17:10:40.665000+0000",
      "content_href": "/r/meirl/comments/1mhb71m/meirl/",
      "content_preview": "",
      "flair": [],
      "thumbnail_url": "https://preview.redd.it/9z8jfmvbqzgf1.jpeg?width=640&crop=smart&auto=webp&s=1f6de5f8b5b7eb9f818eb03b33914eb5fd3cac68"
    },
    {
      "title": "NotKenM on Hamsters",
      "permalink": "https://www.reddit.com/r/NotKenM/comments/1mhe2i9/notkenm_on_hamsters/",
      "score": 33,
      "comments": 2,
      "post_id": "t3_1mhe2i9",
      "post_type": "image",
      "domain": "i.redd.it",
      "author": "ElGofre",
      "author_id": "t2_c4i2h",
      "subreddit_id": "t5_35lpq",
      "subreddit": "r/NotKenM",
      "created_ts": "2025-08-04T13:53:12.932000+0000",
      "content_href": "https://i.redd.it/qqyckesuc0hf1.png",
      "content_preview": "",
      "flair": [],
      "thumbnail_url": "https://www.redditstatic.com/avatars/defaults/v2/avatar_default_1.png"
    },
    {
      "title": "Not Ken M on LinkedIn",
      "permalink": "https://www.reddit.com/r/NotKenM/comments/1mg40ic/not_ken_m_on_linkedin/",
      "score": 297,
      "comments": 3,
      "post_id": "t3_1mg40ic",
      "post_type": "image",
      "domain": "i.redd.it",
      "author": "dixieblondedyke",
      "author_id": "t2_4r1bjthw",
      "subreddit_id": "t5_35lpq",
      "subreddit": "r/NotKenM",
      "created_ts": "2025-08-02T23:08:40.385000+0000",
      "content_href": "https://i.redd.it/0gnmxi48uogf1.jpeg",
      "content_preview": "",
      "flair": [],
      "thumbnail_url": "https://www.redditstatic.com/avatars/defaults/v2/avatar_default_4.png"
    },
    {
      "title": "maybe maybe maybe",
      "permalink": "https://www.reddit.com/r/NotKenM/comments/1mgiimi/maybe_maybe_maybe/",
      "score": 0,
      "comments": 0,
      "post_id": "t3_1mgiimi",
      "post_type": "crosspost",
      "domain": "v.redd.it",
      "author": "burstmod",
      "author_id": "t2_m2vtj",
      "subreddit_id": "t5_35lpq",
      "subreddit": "r/NotKenM",
      "created_ts": "2025-08-03T12:53:23.122000+0000",
      "content_href": "/r/maybemaybemaybe/comments/1mg7930/maybe_maybe_maybe/",
      "content_preview": "",
      "flair": [],
      "thumbnail_url": "https://external-preview.redd.it/maybe-maybe-maybe-v0-aTNkYnFiOXVtcGdmMat_xFePrjjXpYFgWHAutooJ1THPDbfoU6z0cVVP4uVi.png?format=pjpg&auto=webp&s=ee3a0ba66df755ac856efe2ec06888453ae8ef67"
    },
    {
      "title": "Not Ken M on carcinogens",
      "permalink": "https://www.reddit.com/r/NotKenM/comments/1m9l36y/not_ken_m_on_carcinogens/",
      "score": 27,
      "comments": 1,
      "post_id": "t3_1m9l36y",
      "post_type": "image",
      "domain": "i.imgur.com",
      "author": "Soundwave_47",
      "author_id": "t2_akjjb400",
      "subreddit_id": "t5_35lpq",
      "subreddit": "r/NotKenM",
      "created_ts": "2025-07-26T05:15:02.486000+0000",
      "content_href": "https://i.imgur.com/6GluHeg.png",
      "content_preview": "",
      "flair": [],
      "thumbnail_url": "https://www.redditstatic.com/avatars/defaults/v2/avatar_default_0.png"
    },
    {
      "title": "My own little KenM moment. On a video about “the only Dino never found with T-Rex bite marks”",
      "permalink": "https://www.reddit.com/r/NotKenM/comments/1m7la8l/my_own_little_kenm_moment_on_a_video_about_the/",
      "score": 202,
      "comments": 6,
      "post_id": "t3_1m7la8l",
      "post_type": "image",
      "domain": "i.redd.it",
      "author": "MelaninlyChallenged",
      "author_id": "t2_t5qii",
      "subreddit_id": "t5_35lpq",
      "subreddit": "r/NotKenM",
      "created_ts": "2025-07-23T21:07:54.935000+0000",
      "content_href": "https://i.redd.it/iimv2sdkvoef1.jpeg",
      "content_preview": "",
      "flair": [],
      "thumbnail_url": "https://www.redditstatic.com/avatars/defaults/v2/avatar_default_2.png"
    },
    {
      "title": "Not Ken M on bisexuality",
      "permalink": "https://www.reddit.com/r/NotKenM/comments/1m69zq7/not_ken_m_on_bisexuality/",
      "score": 78,
      "comments": 9,
      "post_id": "t3_1m69zq7",
      "post_type": "image",
      "domain": "i.redd.it",
      "author": "Spready_Unsettling",
      "author_id": "t2_2aafvte8",
      "subreddit_id": "t5_35lpq",
      "subreddit": "r/NotKenM",
      "created_ts": "2025-07-22T09:58:39.262000+0000",
      "content_href": "https://i.redd.it/a661cmw8feef1.png",
      "content_preview": "",
      "flair": [],
      "thumbnail_url": "https://www.redditstatic.com/avatars/defaults/v2/avatar_default_0.png"
    },
    {
      "title": "Ron raised quite a good point",
      "permalink": "https://www.reddit.com/r/NotKenM/comments/1m1hpgs/ron_raised_quite_a_good_point/",
      "score": 476,
      "comments": 4,
      "post_id": "t3_1m1hpgs",
      "post_type": "crosspost",
      "domain": "i.redd.it",
      "author": "uncle_hobo",
      "author_id": "t2_khpk5",
      "subreddit_id": "t5_35lpq",
      "subreddit": "r/NotKenM",
      "created_ts": "2025-07-16T16:46:44.041000+0000",
      "content_href": "/r/technicallythetruth/comments/1m15e2w/ron_raised_quite_a_good_point/",
      "content_preview": "",
      "flair": [],
      "thumbnail_url": "https://preview.redd.it/ron-raised-quite-a-good-point-v0-4fnv8zaqk6df1.jpeg?width=640&crop=smart&auto=webp&s=c729321a297bf0747a528946c2d9dbece0d6a16c"
    },
    {
      "title": "NotKenM on dropping coins",
      "permalink": "https://www.reddit.com/r/NotKenM/comments/1m0h9l0/notkenm_on_dropping_coins/",
      "score": 170,
      "comments": 2,
      "post_id": "t3_1m0h9l0",
      "post_type": "image",
      "domain": "i.imgur.com",
      "author": "Tortoisesalltheway",
      "author_id": "t2_1m5hql8s",
      "subreddit_id": "t5_35lpq",
      "subreddit": "r/NotKenM",
      "created_ts": "2025-07-15T13:06:17.799000+0000",
      "content_href": "https://i.imgur.com/rH6RZeB.jpeg",
      "content_preview": "",
      "flair": [],
      "thumbnail_url": "https://www.redditstatic.com/avatars/defaults/v2/avatar_default_4.png"
    },
    {
      "title": "Not Ken M on Bryan Cranston",
      "permalink": "https://www.reddit.com/r/NotKenM/comments/1lxr8sh/not_ken_m_on_bryan_cranston/",
      "score": 217,
      "comments": 9,
      "post_id": "t3_1lxr8sh",
      "post_type": "image",
      "domain": "i.redd.it",
      "author": "ProfessorMarth",
      "author_id": "t2_xtmwk",
      "subreddit_id": "t5_35lpq",
      "subreddit": "r/NotKenM",
      "created_ts": "2025-07-12T04:10:57.496000+0000",
      "content_href": "https://i.redd.it/z7t67vm3cdcf1.png",
      "content_preview": "",
      "flair": [],
      "thumbnail_url": "https://www.redditstatic.com/avatars/defaults/v2/avatar_default_4.png"
    },
    {
      "title": "Pastor says",
      "permalink": "https://www.reddit.com/r/NotKenM/comments/1lqoqo9/pastor_says/",
      "score": 1006,
      "comments": 9,
      "post_id": "t3_1lqoqo9",
      "post_type": "image",
      "domain": "i.redd.it",
      "author": "Smiling_longhair6870",
      "author_id": "t2_fig05blo",
      "subreddit_id": "t5_35lpq",
      "subreddit": "r/NotKenM",
      "created_ts": "2025-07-03T12:48:52.433000+0000",
      "content_href": "https://i.redd.it/gykindvaonaf1.png",
      "content_preview": "",
      "flair": [],
      "thumbnail_url": "https://preview.redd.it/pastor-says-v0-gykindvaonaf1.png?width=640&crop=smart&auto=webp&s=02d929fbec1e201081cb17593d08d3513dc049dd"
    },
    {
      "title": "NotKenM on conception",
      "permalink": "https://www.reddit.com/r/NotKenM/comments/1lnjtzr/notkenm_on_conception/",
      "score": 454,
      "comments": 5,
      "post_id": "t3_1lnjtzr",
      "post_type": "image",
      "domain": "i.redd.it",
      "author": "ElGofre",
      "author_id": "t2_c4i2h",
      "subreddit_id": "t5_35lpq",
      "subreddit": "r/NotKenM",
      "created_ts": "2025-06-29T17:07:37.527000+0000",
      "content_href": "https://i.redd.it/rbpbvmerew9f1.jpeg",
      "content_preview": "",
      "flair": [],
      "thumbnail_url": "https://www.redditstatic.com/avatars/defaults/v2/avatar_default_1.png"
    },
    {
      "title": "Ethyl didn't hear anything.",
      "permalink": "https://www.reddit.com/r/NotKenM/comments/1ljxr1b/ethyl_didnt_hear_anything/",
      "score": 861,
      "comments": 12,
      "post_id": "t3_1ljxr1b",
      "post_type": "crosspost",
      "domain": "i.redd.it",
      "author": "Amateurlapse",
      "author_id": "t2_3177ftg",
      "subreddit_id": "t5_35lpq",
      "subreddit": "r/NotKenM",
      "created_ts": "2025-06-25T05:46:25.900000+0000",
      "content_href": "/r/BoomersBeingFools/comments/1lji2la/ethyl_didnt_hear_anything/",
      "content_preview": "",
      "flair": [],
      "thumbnail_url": "https://preview.redd.it/ethyl-didnt-hear-anything-v0-wkltd2vzyw8f1.jpeg?width=640&crop=smart&auto=webp&s=cfc9e5b2004f420f1bc50b9e9739e568441f1dbc"
    },
    {
      "title": "Not Ken M on houses",
      "permalink": "https://www.reddit.com/r/NotKenM/comments/1lka4vo/not_ken_m_on_houses/",
      "score": 35,
      "comments": 1,
      "post_id": "t3_1lka4vo",
      "post_type": "gallery",
      "domain": "reddit.com",
      "author": "Noodles_fluffy",
      "author_id": "t2_x6let",
      "subreddit_id": "t5_35lpq",
      "subreddit": "r/NotKenM",
      "created_ts": "2025-06-25T16:22:23.883000+0000",
      "content_href": "https://www.reddit.com/gallery/1lka4vo",
      "content_preview": "",
      "flair": [],
      "thumbnail_url": "https://preview.redd.it/not-ken-m-on-houses-v0-wa4de9o3n39f1.jpg?width=640&crop=smart&auto=webp&s=80588e45abd252149267125e4ae8c9738c9ce454"
    },
    {
      "title": "On tree assassins…",
      "permalink": "https://www.reddit.com/r/NotKenM/comments/1lj1njj/on_tree_assassins/",
      "score": 61,
      "comments": 1,
      "post_id": "t3_1lj1njj",
      "post_type": "image",
      "domain": "i.redd.it",
      "author": "NWMossBack",
      "author_id": "t2_sxh11",
      "subreddit_id": "t5_35lpq",
      "subreddit": "r/NotKenM",
      "created_ts": "2025-06-24T04:15:20.995000+0000",
      "content_href": "https://i.redd.it/pilck57hws8f1.jpeg",
      "content_preview": "",
      "flair": [],
      "thumbnail_url": "https://www.redditstatic.com/avatars/defaults/v2/avatar_default_5.png"
    },
    {
      "title": "Herm",
      "permalink": "https://www.reddit.com/r/NotKenM/comments/1li9xi2/herm/",
      "score": 196,
      "comments": 1,
      "post_id": "t3_1li9xi2",
      "post_type": "image",
      "domain": "i.redd.it",
      "author": "Lowgynn",
      "author_id": "t2_m1px4jxgh",
      "subreddit_id": "t5_35lpq",
      "subreddit": "r/NotKenM",
      "created_ts": "2025-06-23T06:58:10.593000+0000",
      "content_href": "https://i.redd.it/d6pg5k9mkm8f1.jpeg",
      "content_preview": "",
      "flair": [],
      "thumbnail_url": "https://styles.redditmedia.com/t5_9mi9hy/styles/profileIcon_k692tjlnlrje1.png?width=64&height=64&frame=1&auto=webp&crop=64%3A64%2Csmart&s=86a6e25dba901c20be912076e39baca397275ef4"
    },
    {
      "title": "Not Ken M on the Lone Star tick",
      "permalink": "https://www.reddit.com/r/NotKenM/comments/1lhh3c3/not_ken_m_on_the_lone_star_tick/",
      "score": 127,
      "comments": 3,
      "post_id": "t3_1lhh3c3",
      "post_type": "image",
      "domain": "i.imgur.com",
      "author": "Soundwave_47",
      "author_id": "t2_akjjb400",
      "subreddit_id": "t5_35lpq",
      "subreddit": "r/NotKenM",
      "created_ts": "2025-06-22T06:18:20.015000+0000",
      "content_href": "https://i.imgur.com/D7fNegB.png",
      "content_preview": "",
      "flair": [],
      "thumbnail_url": "https://www.redditstatic.com/avatars/defaults/v2/avatar_default_0.png"
    },
    {
      "title": "NotKen debating COVID deaths",
      "permalink": "https://www.reddit.com/r/NotKenM/comments/1le6nk3/notken_debating_covid_deaths/",
      "score": 279,
      "comments": 10,
      "post_id": "t3_1le6nk3",
      "post_type": "image",
      "domain": "i.redd.it",
      "author": "micholob",
      "author_id": "t2_975cf",
      "subreddit_id": "t5_35lpq",
      "subreddit": "r/NotKenM",
      "created_ts": "2025-06-18T03:07:44.946000+0000",
      "content_href": "https://i.redd.it/4bysbyzxql7f1.jpeg",
      "content_preview": "",
      "flair": [],
      "thumbnail_url": "https://preview.redd.it/notken-debating-covid-deaths-v0-4bysbyzxql7f1.jpeg?width=640&crop=smart&auto=webp&s=3710021483c3f5834167daeeb91b401a4895bc38"
    },
    {
      "title": "Not KenM on being shot",
      "permalink": "https://www.reddit.com/r/NotKenM/comments/1lcse45/not_kenm_on_being_shot/",
      "score": 103,
      "comments": 2,
      "post_id": "t3_1lcse45",
      "post_type": "image",
      "domain": "i.redd.it",
      "author": "Furaskjoldr",
      "author_id": "t2_2a2dnf72",
      "subreddit_id": "t5_35lpq",
      "subreddit": "r/NotKenM",
      "created_ts": "2025-06-16T13:10:09.327000+0000",
      "content_href": "https://i.redd.it/yqfyphmlga7f1.jpeg",
      "content_preview": "",
      "flair": [],
      "thumbnail_url": "https://www.redditstatic.com/avatars/defaults/v2/avatar_default_6.png"
    },
    {
      "title": "A woman posted about planning a gender reveal, and a guy kept commenting about indecent exposure - apparently he thought a gender reveal party was a bunch of adults flashing their junk at each other. 🤦🏻‍♀️",
      "permalink": "https://www.reddit.com/r/NotKenM/comments/1lcp50c/a_woman_posted_about_planning_a_gender_reveal_and/",
      "score": 81,
      "comments": 8,
      "post_id": "t3_1lcp50c",
      "post_type": "crosspost",
      "domain": "reddit.com",
      "author": "happycabinsong",
      "author_id": "t2_hu5rji2",
      "subreddit_id": "t5_35lpq",
      "subreddit": "r/NotKenM",
      "created_ts": "2025-06-16T10:17:35.494000+0000",
      "content_href": "/r/nextdoor/comments/1lbmzaz/a_woman_posted_about_planning_a_gender_reveal_and/",
      "content_preview": "",
      "flair": [],
      "thumbnail_url": "https://styles.redditmedia.com/t5_5uoc0/styles/profileIcon_jjwtxspqdyxe1.jpeg?width=64&height=64&frame=1&auto=webp&crop=64%3A64%2Csmart&s=bfbd6d59f7cd2e594cb0997268328cc97cfe3b4f"
    },
    {
      "title": "Not Ken M on dramatic effect",
      "permalink": "https://www.reddit.com/r/NotKenM/comments/1lby8vy/not_ken_m_on_dramatic_effect/",
      "score": 459,
      "comments": 4,
      "post_id": "t3_1lby8vy",
      "post_type": "image",
      "domain": "i.redd.it",
      "author": "Fortanono",
      "author_id": "t2_jpm31",
      "subreddit_id": "t5_35lpq",
      "subreddit": "r/NotKenM",
      "created_ts": "2025-06-15T11:35:41.140000+0000",
      "content_href": "https://i.redd.it/9ds4mhxsu27f1.jpeg",
      "content_preview": "",
      "flair": [],
      "thumbnail_url": "https://www.redditstatic.com/avatars/defaults/v2/avatar_default_5.png"
    },
    {
      "title": "NotKenM on having an injury looked at",
      "permalink": "https://www.reddit.com/r/NotKenM/comments/1l6zlhw/notkenm_on_having_an_injury_looked_at/",
      "score": 243,
      "comments": 4,
      "post_id": "t3_1l6zlhw",
      "post_type": "image",
      "domain": "i.redd.it",
      "author": "ardotschgi",
      "author_id": "t2_17iaw0",
      "subreddit_id": "t5_35lpq",
      "subreddit": "r/NotKenM",
      "created_ts": "2025-06-09T08:37:00.625000+0000",
      "content_href": "https://i.redd.it/ai329glh5v5f1.png",
      "content_preview": "",
      "flair": [],
      "thumbnail_url": "https://preview.redd.it/notkenm-on-having-an-injury-looked-at-v0-ai329glh5v5f1.png?width=640&crop=smart&auto=webp&s=cfc2e9f3e89810b5b397846f6109bee95a5c8bfd"
    },
    {
      "title": "on. mario",
      "permalink": "https://www.reddit.com/r/NotKenM/comments/1l6iz97/on_mario/",
      "score": 47,
      "comments": 0,
      "post_id": "t3_1l6iz97",
      "post_type": "crosspost",
      "domain": "i.redd.it",
      "author": "taytek",
      "author_id": "t2_2qzoh6ap",
      "subreddit_id": "t5_35lpq",
      "subreddit": "r/NotKenM",
      "created_ts": "2025-06-08T18:19:50.207000+0000",
      "content_href": "/r/comedyheaven/comments/1l6e6gu/on_mario/",
      "content_preview": "",
      "flair": [],
      "thumbnail_url": "https://preview.redd.it/v1wg0bsvwp5f1.jpeg?width=640&crop=smart&auto=webp&s=1dca5da1bb083d87559e6814267688753834dabe"
    },
    {
      "title": "Close the deal!",
      "permalink": "https://www.reddit.com/r/NotKenM/comments/1l5jm0l/close_the_deal/",
      "score": 330,
      "comments": 1,
      "post_id": "t3_1l5jm0l",
      "post_type": "crosspost",
      "domain": "i.redd.it",
      "author": "Razmpoosh",
      "author_id": "t2_1qxt623t",
      "subreddit_id": "t5_35lpq",
      "subreddit": "r/NotKenM",
      "created_ts": "2025-06-07T12:25:26.576000+0000",
      "content_href": "/r/madlads/comments/1l51geg/close_the_deal/",
      "content_preview": "",
      "flair": [],
      "thumbnail_url": "https://www.redditstatic.com/avatars/defaults/v2/avatar_default_1.png"
    },
    {
      "title": "NotKenM on diamonds",
      "permalink": "https://www.reddit.com/r/NotKenM/comments/1l5sd1h/notkenm_on_diamonds/",
      "score": 42,
      "comments": 0,
      "post_id": "t3_1l5sd1h",
      "post_type": "image",
      "domain": "i.redd.it",
      "author": "deeelighted",
      "author_id": "t2_a6uea3cb",
      "subreddit_id": "t5_35lpq",
      "subreddit": "r/NotKenM",
      "created_ts": "2025-06-07T18:58:15.066000+0000",
      "content_href": "https://i.redd.it/3jwvr2nfyj5f1.png",
      "content_preview": "",
      "flair": [],
      "thumbnail_url": "https://preview.redd.it/notkenm-on-diamonds-v0-3jwvr2nfyj5f1.png?width=640&crop=smart&auto=webp&s=7edf0bdc866d8e586db026630e519fa6274751e5"
    },
    {
      "title": "Not Ken M on Tattoos",
      "permalink": "https://www.reddit.com/r/NotKenM/comments/1l4kavl/not_ken_m_on_tattoos/",
      "score": 438,
      "comments": 4,
      "post_id": "t3_1l4kavl",
      "post_type": "image",
      "domain": "i.redd.it",
      "author": "Zacurnia_Tate",
      "author_id": "t2_11fqf02q",
      "subreddit_id": "t5_35lpq",
      "subreddit": "r/NotKenM",
      "created_ts": "2025-06-06T05:07:09.926000+0000",
      "content_href": "https://i.redd.it/nnyp1fbbp85f1.jpeg",
      "content_preview": "",
      "flair": [],
      "thumbnail_url": "https://preview.redd.it/not-ken-m-on-tattoos-v0-nnyp1fbbp85f1.jpeg?width=640&crop=smart&auto=webp&s=470e6928180995ed9e1e960825868790d22ad870"
    },
    {
      "title": "Just got trolled by NotKenM",
      "permalink": "https://www.reddit.com/r/NotKenM/comments/1l2di40/just_got_trolled_by_notkenm/",
      "score": 147,
      "comments": 17,
      "post_id": "t3_1l2di40",
      "post_type": "image",
      "domain": "i.redd.it",
      "author": "serieousbanana",
      "author_id": "t2_63aie86n",
      "subreddit_id": "t5_35lpq",
      "subreddit": "r/NotKenM",
      "created_ts": "2025-06-03T14:34:30.907000+0000",
      "content_href": "https://i.redd.it/stzrz5ws3q4f1.png",
      "content_preview": "",
      "flair": [],
      "thumbnail_url": "https://preview.redd.it/just-got-trolled-by-notkenm-v0-stzrz5ws3q4f1.png?width=640&crop=smart&auto=webp&s=cf414172967a94ebad68eb5744decb4f92bf60f5"
    },
    {
      "title": "Not Ken M on recumbent bikes",
      "permalink": "https://www.reddit.com/r/NotKenM/comments/1l0akcs/not_ken_m_on_recumbent_bikes/",
      "score": 85,
      "comments": 3,
      "post_id": "t3_1l0akcs",
      "post_type": "gallery",
      "domain": "reddit.com",
      "author": "Spready_Unsettling",
      "author_id": "t2_2aafvte8",
      "subreddit_id": "t5_35lpq",
      "subreddit": "r/NotKenM",
      "created_ts": "2025-05-31T23:22:26.093000+0000",
      "content_href": "https://www.reddit.com/gallery/1l0akcs",
      "content_preview": "",
      "flair": [],
      "thumbnail_url": "https://www.redditstatic.com/avatars/defaults/v2/avatar_default_0.png"
    },
    {
      "title": "On Autism",
      "permalink": "https://www.reddit.com/r/NotKenM/comments/1kzuatt/on_autism/",
      "score": 486,
      "comments": 4,
      "post_id": "t3_1kzuatt",
      "post_type": "image",
      "domain": "i.redd.it",
      "author": "jarbsatat",
      "author_id": "t2_17oc4yeb",
      "subreddit_id": "t5_35lpq",
      "subreddit": "r/NotKenM",
      "created_ts": "2025-05-31T10:54:01.622000+0000",
      "content_href": "https://i.redd.it/1d0nru9ql34f1.jpeg",
      "content_preview": "",
      "flair": [],
      "thumbnail_url": "https://preview.redd.it/1d0nru9ql34f1.jpeg?width=640&crop=smart&auto=webp&s=78b1b9ac580f3f0e50d66ca88143d818f0979b48"
    },
    {
      "title": "Wild accusations",
      "permalink": "https://www.reddit.com/r/NotKenM/comments/1kzscwy/wild_accusations/",
      "score": 394,
      "comments": 0,
      "post_id": "t3_1kzscwy",
      "post_type": "image",
      "domain": "i.redd.it",
      "author": "BungaBungaBroBro",
      "author_id": "t2_mgs1q",
      "subreddit_id": "t5_35lpq",
      "subreddit": "r/NotKenM",
      "created_ts": "2025-05-31T08:40:49.274000+0000",
      "content_href": "https://i.redd.it/cn3klgpyx24f1.jpeg",
      "content_preview": "",
      "flair": [],
      "thumbnail_url": "https://www.redditstatic.com/avatars/defaults/v2/avatar_default_6.png"
    },
    {
      "title": "Whoa Tyranny at McDonalds.",
      "permalink": "https://www.reddit.com/r/NotKenM/comments/1kyyki1/whoa_tyranny_at_mcdonalds/",
      "score": 15,
      "comments": 1,
      "post_id": "t3_1kyyki1",
      "post_type": "crosspost",
      "domain": "reddit.com",
      "author": "MangrovesAndMahi",
      "author_id": "t2_1kg6durb0m",
      "subreddit_id": "t5_35lpq",
      "subreddit": "r/NotKenM",
      "created_ts": "2025-05-30T07:56:45.896000+0000",
      "content_href": "/r/oldpeoplefacebook/comments/1kysee4/whoa_tyranny_at_mcdonalds/",
      "content_preview": "",
      "flair": [],
      "thumbnail_url": "https://www.redditstatic.com/avatars/defaults/v2/avatar_default_6.png"
    },
    {
      "title": "Not Ken M on..Ken M",
      "permalink": "https://www.reddit.com/r/NotKenM/comments/1kx9dlz/not_ken_m_onken_m/",
      "score": 126,
      "comments": 3,
      "post_id": "t3_1kx9dlz",
      "post_type": "crosspost",
      "domain": "v.redd.it",
      "author": "BluntTruthGentleman",
      "author_id": "t2_dm29p",
      "subreddit_id": "t5_35lpq",
      "subreddit": "r/NotKenM",
      "created_ts": "2025-05-28T05:40:53.968000+0000",
      "content_href": "/r/SipsTea/comments/1kx0a1t/professional_hater/",
      "content_preview": "",
      "flair": [],
      "thumbnail_url": "https://external-preview.redd.it/professional-hater-v0-azk0MGJlOWpkZTNmMaZS8pwNJ9Q3nLFUTYsiOZ4I_84gCRGoUxbwyfqbJ8Dg.png?format=pjpg&auto=webp&s=95b02aa5ddbf3c5c542eab513d96dd9f771f198a"
    },
    {
      "title": "NotKenM on drugs",
      "permalink": "https://www.reddit.com/r/NotKenM/comments/1kvwkbq/notkenm_on_drugs/",
      "score": 100,
      "comments": 7,
      "post_id": "t3_1kvwkbq",
      "post_type": "image",
      "domain": "i.redd.it",
      "author": "Goobzgoob",
      "author_id": "t2_9uturynts",
      "subreddit_id": "t5_35lpq",
      "subreddit": "r/NotKenM",
      "created_ts": "2025-05-26T15:01:53.111000+0000",
      "content_href": "https://i.redd.it/brdmql4e553f1.jpeg",
      "content_preview": "",
      "flair": [],
      "thumbnail_url": "https://styles.redditmedia.com/t5_8a0l75/styles/profileIcon_w08ts1rmhnvd1.jpeg?width=64&height=64&frame=1&auto=webp&crop=64%3A64%2Csmart&s=cad96d5883b557a92be43c3a1fb8eb75d027cb56"
    },
    {
      "title": "NotKenM on coughing in classical performances.",
      "permalink": "https://www.reddit.com/r/NotKenM/comments/1kupewf/notkenm_on_coughing_in_classical_performances/",
      "score": 423,
      "comments": 13,
      "post_id": "t3_1kupewf",
      "post_type": "image",
      "domain": "i.redd.it",
      "author": "Possibly_Parker",
      "author_id": "t2_2fggwz7v",
      "subreddit_id": "t5_35lpq",
      "subreddit": "r/NotKenM",
      "created_ts": "2025-05-25T00:00:52.752000+0000",
      "content_href": "https://i.redd.it/315zi3dqjt2f1.jpeg",
      "content_preview": "",
      "flair": [],
      "thumbnail_url": "https://preview.redd.it/notkenm-on-coughing-in-classical-performances-v0-315zi3dqjt2f1.jpeg?width=640&crop=smart&auto=webp&s=5c284d60ff74c2e8deb6c3c3aac827b49798f407"
    },
    {
      "title": "On salads",
      "permalink": "https://www.reddit.com/r/NotKenM/comments/1kunv6b/on_salads/",
      "score": 41,
      "comments": 6,
      "post_id": "t3_1kunv6b",
      "post_type": "image",
      "domain": "i.redd.it",
      "author": "ChoixDansLaDate",
      "author_id": "t2_56okdtmk",
      "subreddit_id": "t5_35lpq",
      "subreddit": "r/NotKenM",
      "created_ts": "2025-05-24T22:42:41.056000+0000",
      "content_href": "https://i.redd.it/76fvke3s5t2f1.jpeg",
      "content_preview": "",
      "flair": [],
      "thumbnail_url": "https://preview.redd.it/76fvke3s5t2f1.jpeg?width=640&crop=smart&auto=webp&s=a8dbf928626133b21388b0d7d7112661062dad36"
    },
    {
      "title": "Cuckold music",
      "permalink": "https://www.reddit.com/r/NotKenM/comments/1ksl4jb/cuckold_music/",
      "score": 77,
      "comments": 4,
      "post_id": "t3_1ksl4jb",
      "post_type": "crosspost",
      "domain": "i.redd.it",
      "author": "BluntTruthGentleman",
      "author_id": "t2_dm29p",
      "subreddit_id": "t5_35lpq",
      "subreddit": "r/NotKenM",
      "created_ts": "2025-05-22T07:52:50.937000+0000",
      "content_href": "/r/comedyheaven/comments/1ksbkxn/cuckold_music/",
      "content_preview": "",
      "flair": [],
      "thumbnail_url": "https://preview.redd.it/cuckold-music-v0-j0qc967ms72f1.jpeg?width=640&crop=smart&auto=webp&s=8e799d382fb3d6c2b934321548c78ca6fd6ce782"
    },
    {
      "title": "NotKenM on dads",
      "permalink": "https://www.reddit.com/r/NotKenM/comments/1kqa22p/notkenm_on_dads/",
      "score": 2639,
      "comments": 5,
      "post_id": "t3_1kqa22p",
      "post_type": "image",
      "domain": "i.redd.it",
      "author": "ElGofre",
      "author_id": "t2_c4i2h",
      "subreddit_id": "t5_35lpq",
      "subreddit": "r/NotKenM",
      "created_ts": "2025-05-19T12:09:36.426000+0000",
      "content_href": "https://i.redd.it/v0na3b89cq1f1.jpeg",
      "content_preview": "",
      "flair": [],
      "thumbnail_url": "https://www.redditstatic.com/avatars/defaults/v2/avatar_default_1.png"
    },
    {
      "title": "Ken's Eating Choices",
      "permalink": "https://www.reddit.com/r/NotKenM/comments/1kparlm/kens_eating_choices/",
      "score": 112,
      "comments": 7,
      "post_id": "t3_1kparlm",
      "post_type": "crosspost",
      "domain": "i.redd.it",
      "author": "solorush",
      "author_id": "t2_f7kgc",
      "subreddit_id": "t5_35lpq",
      "subreddit": "r/NotKenM",
      "created_ts": "2025-05-18T03:34:58.991000+0000",
      "content_href": "/r/LinkedInLunatics/comments/1koqc4f/kens_eating_choices/",
      "content_preview": "",
      "flair": [],
      "thumbnail_url": "https://preview.redd.it/kens-eating-choices-v0-pnfqawfiqb1f1.png?width=640&crop=smart&auto=webp&s=bdd977d2f5a1db23d4f76398f2c416dc28144e89"
    },
    {
      "title": "Lithium bomb",
      "permalink": "https://www.reddit.com/r/NotKenM/comments/1ko2lt7/lithium_bomb/",
      "score": 189,
      "comments": 8,
      "post_id": "t3_1ko2lt7",
      "post_type": "crosspost",
      "domain": "reddit.com",
      "author": "uncle_hobo",
      "author_id": "t2_khpk5",
      "subreddit_id": "t5_35lpq",
      "subreddit": "r/NotKenM",
      "created_ts": "2025-05-16T14:43:13.831000+0000",
      "content_href": "/r/CuratedTumblr/comments/1knvm6u/lithium_bomb/",
      "content_preview": "",
      "flair": [],
      "thumbnail_url": "https://preview.redd.it/lithium-bomb-v0-k2dz6c0ur31f1.jpg?width=640&crop=smart&auto=webp&s=0525c1c9d1205fb5533c5032dd51125a601f92b8"
    },
    {
      "title": "Not KenM on Meat",
      "permalink": "https://www.reddit.com/r/NotKenM/comments/1klrcs9/not_kenm_on_meat/",
      "score": 1380,
      "comments": 49,
      "post_id": "t3_1klrcs9",
      "post_type": "image",
      "domain": "i.redd.it",
      "author": "aye_eyes",
      "author_id": "t2_rna5j",
      "subreddit_id": "t5_35lpq",
      "subreddit": "r/NotKenM",
      "created_ts": "2025-05-13T17:06:33.515000+0000",
      "content_href": "https://i.redd.it/1w3nhtrnzk0f1.png",
      "content_preview": "",
      "flair": [],
      "thumbnail_url": "https://www.redditstatic.com/avatars/defaults/v2/avatar_default_7.png"
    },
    {
      "title": "Swimsplaining",
      "permalink": "https://www.reddit.com/r/NotKenM/comments/1kmmo0n/swimsplaining/",
      "score": 7,
      "comments": 1,
      "post_id": "t3_1kmmo0n",
      "post_type": "crosspost",
      "domain": "reddit.com",
      "author": "oli_99",
      "author_id": "t2_hlxdu",
      "subreddit_id": "t5_35lpq",
      "subreddit": "r/NotKenM",
      "created_ts": "2025-05-14T18:29:50.509000+0000",
      "content_href": "/r/dontyouknowwhoiam/comments/1kmlk9e/swimsplaining/",
      "content_preview": "",
      "flair": [],
      "thumbnail_url": "https://www.redditstatic.com/avatars/defaults/v2/avatar_default_2.png"
    },
    {
      "title": "Bear left",
      "permalink": "https://www.reddit.com/r/NotKenM/comments/1kj4hqd/bear_left/",
      "score": 0,
      "comments": 42,
      "post_id": "t3_1kj4hqd",
      "post_type": "gallery",
      "domain": "reddit.com",
      "author": "pee_nut_ninja",
      "author_id": "t2_ecoorncww",
      "subreddit_id": "t5_35lpq",
      "subreddit": "r/NotKenM",
      "created_ts": "2025-05-10T07:17:55.109000+0000",
      "content_href": "https://www.reddit.com/gallery/1kj4hqd",
      "content_preview": "",
      "flair": [],
      "thumbnail_url": "https://preview.redd.it/ly8f1py0owze1.jpg?width=640&crop=smart&auto=webp&s=5d1c0d4559b7e06d5a399e6374c0373ab136eb54"
    },
    {
      "title": "NotKenM on John Lennon",
      "permalink": "https://www.reddit.com/r/NotKenM/comments/1kfj5w4/notkenm_on_john_lennon/",
      "score": 69,
      "comments": 12,
      "post_id": "t3_1kfj5w4",
      "post_type": "image",
      "domain": "i.redd.it",
      "author": "brothermanbaj",
      "author_id": "t2_c25p447r",
      "subreddit_id": "t5_35lpq",
      "subreddit": "r/NotKenM",
      "created_ts": "2025-05-05T18:34:33.612000+0000",
      "content_href": "https://i.redd.it/v9nfrxx6c0ze1.png",
      "content_preview": "",
      "flair": [],
      "thumbnail_url": "https://www.redditstatic.com/avatars/defaults/v2/avatar_default_7.png"
    },
    {
      "title": "The BBC has spelling errors because they use British English",
      "permalink": "https://www.reddit.com/r/NotKenM/comments/1kd0rne/the_bbc_has_spelling_errors_because_they_use/",
      "score": 124,
      "comments": 4,
      "post_id": "t3_1kd0rne",
      "post_type": "crosspost",
      "domain": "i.redd.it",
      "author": "codexlogic",
      "author_id": "t2_v22q6",
      "subreddit_id": "t5_35lpq",
      "subreddit": "r/NotKenM",
      "created_ts": "2025-05-02T13:19:35.441000+0000",
      "content_href": "/r/USdefaultism/comments/1kcnm9l/the_bbc_has_spelling_errors_because_they_use/",
      "content_preview": "",
      "flair": [],
      "thumbnail_url": "https://preview.redd.it/the-bbc-has-spelling-errors-because-they-use-british-english-v0-1dk6oftsf9ye1.png?width=640&crop=smart&auto=webp&s=9f55f88453b50f3ab18deefbad39bbf43ac69d7f"
    },
    {
      "title": "NotKenM on Birth Control",
      "permalink": "https://www.reddit.com/r/NotKenM/comments/1kb8jhb/notkenm_on_birth_control/",
      "score": 929,
      "comments": 3,
      "post_id": "t3_1kb8jhb",
      "post_type": "image",
      "domain": "i.redd.it",
      "author": "uqde",
      "author_id": "t2_psyfzgr9",
      "subreddit_id": "t5_35lpq",
      "subreddit": "r/NotKenM",
      "created_ts": "2025-04-30T05:03:41.008000+0000",
      "content_href": "https://i.redd.it/zwvaoyixmwxe1.jpeg",
      "content_preview": "",
      "flair": [],
      "thumbnail_url": "https://preview.redd.it/notkenm-on-birth-control-v0-zwvaoyixmwxe1.jpeg?width=640&crop=smart&auto=webp&s=50b858d1d49a678ffecd4afe5474745b8219a70c"
    }
  ],
  "scraped_at": "2025-09-02T09:35:56.265129"
}