{
  "subreddit": "penang",
  "url": "https://www.reddit.com/r/penang",
  "meta": {
    "title": "r/Penang",
    "members_text": "1,291,954"
  },
  "posts": [
    {
      "title": "Mosaic/Old Tiles",
      "permalink": "https://www.reddit.com/r/penang/comments/1n5prli/mosaicold_tiles/",
      "score": 7,
      "comments": 2,
      "post_id": "t3_1n5prli",
      "post_type": "gallery",
      "domain": "reddit.com",
      "author": "ChampionshipAny3714",
      "author_id": "t2_881dme0k",
      "subreddit_id": "t5_2snuj",
      "subreddit": "r/penang",
      "created_ts": "2025-09-01T14:11:52.975000+0000",
      "content_href": "https://www.reddit.com/gallery/1n5prli",
      "content_preview": "",
      "flair": [],
      "thumbnail_url": "https://preview.redd.it/mosaic-old-tiles-v0-6psfseks9kmf1.jpg?width=640&crop=smart&auto=webp&s=7d8bf63670eb565ffb1c4b5d458a79bb14d61ee6"
    },
    {
      "title": "hiking, running",
      "permalink": "https://www.reddit.com/r/penang/comments/1n50d0m/hiking_running/",
      "score": 2,
      "comments": 1,
      "post_id": "t3_1n50d0m",
      "post_type": "text",
      "domain": "self.penang",
      "author": "wankeli",
      "author_id": "t2_8xd1iikj",
      "subreddit_id": "t5_2snuj",
      "subreddit": "r/penang",
      "created_ts": "2025-08-31T17:16:55.137000+0000",
      "content_href": "https://www.reddit.com/r/penang/comments/1n50d0m/hiking_running/",
      "content_preview": "",
      "flair": [
        "Discussion"
      ],
      "thumbnail_url": "https://www.redditstatic.com/avatars/defaults/v2/avatar_default_3.png"
    },
    {
      "title": "Weather In October",
      "permalink": "https://www.reddit.com/r/penang/comments/1n53h0v/weather_in_october/",
      "score": 0,
      "comments": 4,
      "post_id": "t3_1n53h0v",
      "post_type": "text",
      "domain": "self.penang",
      "author": "FireOnIce30",
      "author_id": "t2_5h6zmkyu",
      "subreddit_id": "t5_2snuj",
      "subreddit": "r/penang",
      "created_ts": "2025-08-31T19:20:01.690000+0000",
      "content_href": "https://www.reddit.com/r/penang/comments/1n53h0v/weather_in_october/",
      "content_preview": "",
      "flair": [
        "Discussion"
      ],
      "thumbnail_url": ""
    },
    {
      "title": "Seeking professional UX/UI coders for project.",
      "permalink": "https://www.reddit.com/r/penang/comments/1n3uf00/seeking_professional_uxui_coders_for_project/",
      "score": 1,
      "comments": 1,
      "post_id": "t3_1n3uf00",
      "post_type": "text",
      "domain": "self.penang",
      "author": "mattydmr2",
      "author_id": "t2_11jrry",
      "subreddit_id": "t5_2snuj",
      "subreddit": "r/penang",
      "created_ts": "2025-08-30T06:19:16.350000+0000",
      "content_href": "https://www.reddit.com/r/penang/comments/1n3uf00/seeking_professional_uxui_coders_for_project/",
      "content_preview": "",
      "flair": [
        "Discussion"
      ],
      "thumbnail_url": "https://www.redditstatic.com/avatars/defaults/v2/avatar_default_6.png"
    },
    {
      "title": "I'm addicted to Pan Mee from Gurney Plaza food court.",
      "permalink": "https://www.reddit.com/r/penang/comments/1n33obb/im_addicted_to_pan_mee_from_gurney_plaza_food/",
      "score": 27,
      "comments": 32,
      "post_id": "t3_1n33obb",
      "post_type": "text",
      "domain": "self.penang",
      "author": "kunyit4lyfe",
      "author_id": "t2_2dam8wm4",
      "subreddit_id": "t5_2snuj",
      "subreddit": "r/penang",
      "created_ts": "2025-08-29T10:24:36.470000+0000",
      "content_href": "https://www.reddit.com/r/penang/comments/1n33obb/im_addicted_to_pan_mee_from_gurney_plaza_food/",
      "content_preview": "",
      "flair": [
        "Discussion"
      ],
      "thumbnail_url": ""
    },
    {
      "title": "Anyone looking for PT ?",
      "permalink": "https://www.reddit.com/r/penang/comments/1n3cewz/anyone_looking_for_pt/",
      "score": 8,
      "comments": 6,
      "post_id": "t3_1n3cewz",
      "post_type": "text",
      "domain": "self.penang",
      "author": "Existing_Memory_7758",
      "author_id": "t2_189f9gbyob",
      "subreddit_id": "t5_2snuj",
      "subreddit": "r/penang",
      "created_ts": "2025-08-29T16:40:46.347000+0000",
      "content_href": "https://www.reddit.com/r/penang/comments/1n3cewz/anyone_looking_for_pt/",
      "content_preview": "",
      "flair": [
        "Discussion"
      ],
      "thumbnail_url": "https://www.redditstatic.com/avatars/defaults/v2/avatar_default_3.png"
    },
    {
      "title": "Penang vs. Sepilok: Malaysia Day 2025",
      "permalink": "https://www.reddit.com/r/penang/comments/1n35l89/penang_vs_sepilok_malaysia_day_2025/",
      "score": 2,
      "comments": 6,
      "post_id": "t3_1n35l89",
      "post_type": "text",
      "domain": "self.penang",
      "author": "CampaignTight1489",
      "author_id": "t2_uxwnkuev",
      "subreddit_id": "t5_2snuj",
      "subreddit": "r/penang",
      "created_ts": "2025-08-29T12:05:19.484000+0000",
      "content_href": "https://www.reddit.com/r/penang/comments/1n35l89/penang_vs_sepilok_malaysia_day_2025/",
      "content_preview": "",
      "flair": [
        "Discussion"
      ],
      "thumbnail_url": "https://www.redditstatic.com/avatars/defaults/v2/avatar_default_7.png"
    },
    {
      "title": "Sunrise, Penang Bridge",
      "permalink": "https://www.reddit.com/r/penang/comments/1n2gcct/sunrise_penang_bridge/",
      "score": 41,
      "comments": 1,
      "post_id": "t3_1n2gcct",
      "post_type": "image",
      "domain": "i.imgur.com",
      "author": "gropbldoppy9",
      "author_id": "t2_1waxlenlku",
      "subreddit_id": "t5_2snuj",
      "subreddit": "r/penang",
      "created_ts": "2025-08-28T16:04:32.433000+0000",
      "content_href": "https://i.imgur.com/XYb2oB7.jpeg",
      "content_preview": "",
      "flair": [
        "Picture"
      ],
      "thumbnail_url": "https://external-preview.redd.it/sunrise-penang-bridge-v0-p_ExutxTL-Y1xTyqNTpQeRQ9hfiTSw5P4cWgX5p8Wsg.jpeg?width=640&crop=smart&auto=webp&s=f9356307ae096786337093029ec94c31b9e04af4"
    },
    {
      "title": "Iconic sunrise view in Penang Island!",
      "permalink": "https://www.reddit.com/r/penang/comments/1n23htb/iconic_sunrise_view_in_penang_island/",
      "score": 104,
      "comments": 2,
      "post_id": "t3_1n23htb",
      "post_type": "image",
      "domain": "i.redd.it",
      "author": "MidValleyGhost",
      "author_id": "t2_1s33lolayl",
      "subreddit_id": "t5_2snuj",
      "subreddit": "r/penang",
      "created_ts": "2025-08-28T05:05:53.734000+0000",
      "content_href": "https://i.redd.it/71whklkq0plf1.jpeg",
      "content_preview": "",
      "flair": [
        "Picture"
      ],
      "thumbnail_url": "https://preview.redd.it/iconic-sunrise-view-in-penang-island-v0-71whklkq0plf1.jpeg?width=640&crop=smart&auto=webp&s=9180b105f687ea87674137517fe1485fe3fd71a2"
    },
    {
      "title": "What is ongoing about YB Fahmi?",
      "permalink": "https://www.reddit.com/r/penang/comments/1n1ih2v/what_is_ongoing_about_yb_fahmi/",
      "score": 7,
      "comments": 1,
      "post_id": "t3_1n1ih2v",
      "post_type": "gallery",
      "domain": "reddit.com",
      "author": "Spirited_Decisions",
      "author_id": "t2_z3njapaod",
      "subreddit_id": "t5_2snuj",
      "subreddit": "r/penang",
      "created_ts": "2025-08-27T14:24:27.218000+0000",
      "content_href": "https://www.reddit.com/gallery/1n1ih2v",
      "content_preview": "",
      "flair": [],
      "thumbnail_url": "https://preview.redd.it/what-is-ongoing-about-yb-fahmi-v0-bn59gpsgnklf1.jpg?width=640&crop=smart&auto=webp&s=378a10a246a7050bd72738a759d26fa1dc8316c0"
    },
    {
      "title": "Athen Fitness is a Terrible gym centre",
      "permalink": "https://www.reddit.com/r/penang/comments/1n0a6on/athen_fitness_is_a_terrible_gym_centre/",
      "score": 23,
      "comments": 9,
      "post_id": "t3_1n0a6on",
      "post_type": "image",
      "domain": "i.redd.it",
      "author": "Candid_Total495",
      "author_id": "t2_1wg4uyn1fk",
      "subreddit_id": "t5_2snuj",
      "subreddit": "r/penang",
      "created_ts": "2025-08-26T02:30:53.552000+0000",
      "content_href": "https://i.redd.it/d0agkwn6z9lf1.jpeg",
      "content_preview": "",
      "flair": [
        "Picture"
      ],
      "thumbnail_url": "https://www.redditstatic.com/avatars/defaults/v2/avatar_default_0.png"
    },
    {
      "title": "If you’re leaving Penang tomorrow. One last meal. Where are you going and why?",
      "permalink": "https://www.reddit.com/r/penang/comments/1mzicbp/if_youre_leaving_penang_tomorrow_one_last_meal/",
      "score": 27,
      "comments": 45,
      "post_id": "t3_1mzicbp",
      "post_type": "text",
      "domain": "self.penang",
      "author": "MidValleyGhost",
      "author_id": "t2_1s33lolayl",
      "subreddit_id": "t5_2snuj",
      "subreddit": "r/penang",
      "created_ts": "2025-08-25T05:44:07.290000+0000",
      "content_href": "https://www.reddit.com/r/penang/comments/1mzicbp/if_youre_leaving_penang_tomorrow_one_last_meal/",
      "content_preview": "",
      "flair": [
        "Discussion"
      ],
      "thumbnail_url": ""
    },
    {
      "title": "I was planning on visiting Malaysia. Please help me out.",
      "permalink": "https://www.reddit.com/r/penang/comments/1n0c9ov/i_was_planning_on_visiting_malaysia_please_help/",
      "score": 0,
      "comments": 23,
      "post_id": "t3_1n0c9ov",
      "post_type": "text",
      "domain": "self.penang",
      "author": "atroxima",
      "author_id": "t2_7pa91i3k",
      "subreddit_id": "t5_2snuj",
      "subreddit": "r/penang",
      "created_ts": "2025-08-26T04:18:43.078000+0000",
      "content_href": "https://www.reddit.com/r/penang/comments/1n0c9ov/i_was_planning_on_visiting_malaysia_please_help/",
      "content_preview": "",
      "flair": [
        "Discussion"
      ],
      "thumbnail_url": ""
    },
    {
      "title": "Penang Short Staycations",
      "permalink": "https://www.reddit.com/r/penang/comments/1mzy05p/penang_short_staycations/",
      "score": 1,
      "comments": 7,
      "post_id": "t3_1mzy05p",
      "post_type": "text",
      "domain": "self.penang",
      "author": "ProblemAdept9913",
      "author_id": "t2_pfwix65h",
      "subreddit_id": "t5_2snuj",
      "subreddit": "r/penang",
      "created_ts": "2025-08-25T18:08:54.454000+0000",
      "content_href": "https://www.reddit.com/r/penang/comments/1mzy05p/penang_short_staycations/",
      "content_preview": "",
      "flair": [
        "Discussion"
      ],
      "thumbnail_url": "https://www.redditstatic.com/avatars/defaults/v2/avatar_default_5.png"
    },
    {
      "title": "Waterless/Nebulizing diffuser brand ?",
      "permalink": "https://www.reddit.com/r/penang/comments/1mzqx86/waterlessnebulizing_diffuser_brand/",
      "score": 1,
      "comments": 1,
      "post_id": "t3_1mzqx86",
      "post_type": "text",
      "domain": "self.penang",
      "author": "WeirdTop1031",
      "author_id": "t2_s6a5gc2mm",
      "subreddit_id": "t5_2snuj",
      "subreddit": "r/penang",
      "created_ts": "2025-08-25T13:45:45.505000+0000",
      "content_href": "https://www.reddit.com/r/penang/comments/1mzqx86/waterlessnebulizing_diffuser_brand/",
      "content_preview": "",
      "flair": [
        "Discussion"
      ],
      "thumbnail_url": ""
    },
    {
      "title": "Are groceries just really expensive in Penang? Or are we doing something wrong?",
      "permalink": "https://www.reddit.com/r/penang/comments/1mz3m7i/are_groceries_just_really_expensive_in_penang_or/",
      "score": 18,
      "comments": 60,
      "post_id": "t3_1mz3m7i",
      "post_type": "text",
      "domain": "self.penang",
      "author": "hdfire21",
      "author_id": "t2_1kvi8dwcnh",
      "subreddit_id": "t5_2snuj",
      "subreddit": "r/penang",
      "created_ts": "2025-08-24T18:37:07.174000+0000",
      "content_href": "https://www.reddit.com/r/penang/comments/1mz3m7i/are_groceries_just_really_expensive_in_penang_or/",
      "content_preview": "",
      "flair": [
        "Discussion"
      ],
      "thumbnail_url": ""
    },
    {
      "title": "Penang City Stadium",
      "permalink": "https://www.reddit.com/r/penang/comments/1myxfwz/penang_city_stadium/",
      "score": 1,
      "comments": 3,
      "post_id": "t3_1myxfwz",
      "post_type": "text",
      "domain": "self.penang",
      "author": "interventiooon",
      "author_id": "t2_9q4iirn3",
      "subreddit_id": "t5_2snuj",
      "subreddit": "r/penang",
      "created_ts": "2025-08-24T14:44:49.721000+0000",
      "content_href": "https://www.reddit.com/r/penang/comments/1myxfwz/penang_city_stadium/",
      "content_preview": "",
      "flair": [
        "Discussion"
      ],
      "thumbnail_url": "https://www.redditstatic.com/avatars/defaults/v2/avatar_default_7.png"
    },
    {
      "title": "Found Intel Mascott logo being used in Bayan Baru workshop",
      "permalink": "https://www.reddit.com/r/penang/comments/1my0z67/found_intel_mascott_logo_being_used_in_bayan_baru/",
      "score": 17,
      "comments": 2,
      "post_id": "t3_1my0z67",
      "post_type": "image",
      "domain": "i.redd.it",
      "author": "Spirited_Decisions",
      "author_id": "t2_z3njapaod",
      "subreddit_id": "t5_2snuj",
      "subreddit": "r/penang",
      "created_ts": "2025-08-23T13:06:28.274000+0000",
      "content_href": "https://i.redd.it/04ujtf8xprkf1.jpeg",
      "content_preview": "",
      "flair": [
        "Picture"
      ],
      "thumbnail_url": "https://preview.redd.it/found-intel-mascott-logo-being-used-in-bayan-baru-workshop-v0-04ujtf8xprkf1.jpeg?width=640&crop=smart&auto=webp&s=58c5a236019fe1fbe8df2f93f20742f7e2118357"
    },
    {
      "title": "Best recommendation for food in Penang & TAMBUN BISCUITS",
      "permalink": "https://www.reddit.com/r/penang/comments/1mxxt14/best_recommendation_for_food_in_penang_tambun/",
      "score": 2,
      "comments": 11,
      "post_id": "t3_1mxxt14",
      "post_type": "text",
      "domain": "self.penang",
      "author": "ThrowRacksAway",
      "author_id": "t2_121d8og37x",
      "subreddit_id": "t5_2snuj",
      "subreddit": "r/penang",
      "created_ts": "2025-08-23T10:22:31.269000+0000",
      "content_href": "https://www.reddit.com/r/penang/comments/1mxxt14/best_recommendation_for_food_in_penang_tambun/",
      "content_preview": "",
      "flair": [
        "Discussion"
      ],
      "thumbnail_url": "https://www.redditstatic.com/avatars/defaults/v2/avatar_default_5.png"
    },
    {
      "title": "Help!! Coffees similar to ORIENTAL KOPI",
      "permalink": "https://www.reddit.com/r/penang/comments/1mxrh26/help_coffees_similar_to_oriental_kopi/",
      "score": 3,
      "comments": 8,
      "post_id": "t3_1mxrh26",
      "post_type": "text",
      "domain": "self.penang",
      "author": "Mysterious_Read9300",
      "author_id": "t2_sd179s5kb",
      "subreddit_id": "t5_2snuj",
      "subreddit": "r/penang",
      "created_ts": "2025-08-23T04:01:11.805000+0000",
      "content_href": "https://www.reddit.com/r/penang/comments/1mxrh26/help_coffees_similar_to_oriental_kopi/",
      "content_preview": "",
      "flair": [
        "Discussion"
      ],
      "thumbnail_url": "https://www.redditstatic.com/avatars/defaults/v2/avatar_default_3.png"
    },
    {
      "title": "What happened to old green house? Closed?",
      "permalink": "https://www.reddit.com/r/penang/comments/1mxp923/what_happened_to_old_green_house_closed/",
      "score": 4,
      "comments": 4,
      "post_id": "t3_1mxp923",
      "post_type": "text",
      "domain": "self.penang",
      "author": "altqq",
      "author_id": "t2_63liw",
      "subreddit_id": "t5_2snuj",
      "subreddit": "r/penang",
      "created_ts": "2025-08-23T02:06:11.878000+0000",
      "content_href": "https://www.reddit.com/r/penang/comments/1mxp923/what_happened_to_old_green_house_closed/",
      "content_preview": "",
      "flair": [
        "Discussion"
      ],
      "thumbnail_url": "https://www.redditstatic.com/avatars/defaults/v2/avatar_default_0.png"
    },
    {
      "title": "Kek Lok Si - Lights",
      "permalink": "https://www.reddit.com/r/penang/comments/1mxrmq9/kek_lok_si_lights/",
      "score": 1,
      "comments": 4,
      "post_id": "t3_1mxrmq9",
      "post_type": "text",
      "domain": "self.penang",
      "author": "Educational_End_9234",
      "author_id": "t2_7t6cpvz2",
      "subreddit_id": "t5_2snuj",
      "subreddit": "r/penang",
      "created_ts": "2025-08-23T04:09:36.624000+0000",
      "content_href": "https://www.reddit.com/r/penang/comments/1mxrmq9/kek_lok_si_lights/",
      "content_preview": "",
      "flair": [
        "Discussion"
      ],
      "thumbnail_url": "https://www.redditstatic.com/avatars/defaults/v2/avatar_default_6.png"
    },
    {
      "title": "Butterworth to George Town",
      "permalink": "https://www.reddit.com/r/penang/comments/1mx0ntz/butterworth_to_george_town/",
      "score": 5,
      "comments": 13,
      "post_id": "t3_1mx0ntz",
      "post_type": "text",
      "domain": "self.penang",
      "author": "saik_lone",
      "author_id": "t2_ml2k7bwv",
      "subreddit_id": "t5_2snuj",
      "subreddit": "r/penang",
      "created_ts": "2025-08-22T08:13:55.337000+0000",
      "content_href": "https://www.reddit.com/r/penang/comments/1mx0ntz/butterworth_to_george_town/",
      "content_preview": "",
      "flair": [
        "Discussion"
      ],
      "thumbnail_url": ""
    },
    {
      "title": "Penang fine dine recommendation",
      "permalink": "https://www.reddit.com/r/penang/comments/1mx3tj3/penang_fine_dine_recommendation/",
      "score": 2,
      "comments": 13,
      "post_id": "t3_1mx3tj3",
      "post_type": "text",
      "domain": "self.penang",
      "author": "WeirdTop1031",
      "author_id": "t2_s6a5gc2mm",
      "subreddit_id": "t5_2snuj",
      "subreddit": "r/penang",
      "created_ts": "2025-08-22T11:24:09.321000+0000",
      "content_href": "https://www.reddit.com/r/penang/comments/1mx3tj3/penang_fine_dine_recommendation/",
      "content_preview": "",
      "flair": [
        "Discussion"
      ],
      "thumbnail_url": ""
    },
    {
      "title": "Bukit Mertajam to Airport",
      "permalink": "https://www.reddit.com/r/penang/comments/1mx38fv/bukit_mertajam_to_airport/",
      "score": 1,
      "comments": 5,
      "post_id": "t3_1mx38fv",
      "post_type": "text",
      "domain": "self.penang",
      "author": "Waste-Survey2588",
      "author_id": "t2_7kf27oye",
      "subreddit_id": "t5_2snuj",
      "subreddit": "r/penang",
      "created_ts": "2025-08-22T10:52:40.318000+0000",
      "content_href": "https://www.reddit.com/r/penang/comments/1mx38fv/bukit_mertajam_to_airport/",
      "content_preview": "",
      "flair": [
        "Discussion"
      ],
      "thumbnail_url": ""
    },
    {
      "title": "Any shop in Penang that sharpens knives? Kitchen knives specifically",
      "permalink": "https://www.reddit.com/r/penang/comments/1mw9xgm/any_shop_in_penang_that_sharpens_knives_kitchen/",
      "score": 3,
      "comments": 11,
      "post_id": "t3_1mw9xgm",
      "post_type": "text",
      "domain": "self.penang",
      "author": "Physical_Lettuce666",
      "author_id": "t2_u01otr44",
      "subreddit_id": "t5_2snuj",
      "subreddit": "r/penang",
      "created_ts": "2025-08-21T12:45:20.323000+0000",
      "content_href": "https://www.reddit.com/r/penang/comments/1mw9xgm/any_shop_in_penang_that_sharpens_knives_kitchen/",
      "content_preview": "",
      "flair": [
        "Discussion"
      ],
      "thumbnail_url": "https://www.redditstatic.com/avatars/defaults/v2/avatar_default_4.png"
    },
    {
      "title": "Looking for a driving school",
      "permalink": "https://www.reddit.com/r/penang/comments/1mw3wjz/looking_for_a_driving_school/",
      "score": 3,
      "comments": 2,
      "post_id": "t3_1mw3wjz",
      "post_type": "text",
      "domain": "self.penang",
      "author": "Competitive-Long3892",
      "author_id": "t2_iormx4uh9",
      "subreddit_id": "t5_2snuj",
      "subreddit": "r/penang",
      "created_ts": "2025-08-21T07:03:54.678000+0000",
      "content_href": "https://www.reddit.com/r/penang/comments/1mw3wjz/looking_for_a_driving_school/",
      "content_preview": "",
      "flair": [
        "Discussion"
      ],
      "thumbnail_url": "https://www.redditstatic.com/avatars/defaults/v2/avatar_default_5.png"
    },
    {
      "title": "Recommendation on reed diffuser",
      "permalink": "https://www.reddit.com/r/penang/comments/1mw1bs4/recommendation_on_reed_diffuser/",
      "score": 3,
      "comments": 10,
      "post_id": "t3_1mw1bs4",
      "post_type": "text",
      "domain": "self.penang",
      "author": "WeirdTop1031",
      "author_id": "t2_s6a5gc2mm",
      "subreddit_id": "t5_2snuj",
      "subreddit": "r/penang",
      "created_ts": "2025-08-21T04:33:39.606000+0000",
      "content_href": "https://www.reddit.com/r/penang/comments/1mw1bs4/recommendation_on_reed_diffuser/",
      "content_preview": "",
      "flair": [
        "Discussion"
      ],
      "thumbnail_url": ""
    },
    {
      "title": "Penang's morning glow!",
      "permalink": "https://www.reddit.com/r/penang/comments/1mv62j7/penangs_morning_glow/",
      "score": 38,
      "comments": 1,
      "post_id": "t3_1mv62j7",
      "post_type": "image",
      "domain": "i.redd.it",
      "author": "MidValleyGhost",
      "author_id": "t2_1s33lolayl",
      "subreddit_id": "t5_2snuj",
      "subreddit": "r/penang",
      "created_ts": "2025-08-20T05:23:31.831000+0000",
      "content_href": "https://i.redd.it/unw84xgl04kf1.jpeg",
      "content_preview": "",
      "flair": [
        "Picture"
      ],
      "thumbnail_url": "https://preview.redd.it/penangs-morning-glow-v0-unw84xgl04kf1.jpeg?width=640&crop=smart&auto=webp&s=3b73ba3bd1bd48278bb1f299dd6b5a152291f9c6"
    },
    {
      "title": "Sightseeing/tourist attractions, eateries, shops around Batu Ferringhi",
      "permalink": "https://www.reddit.com/r/penang/comments/1mv8gup/sightseeingtourist_attractions_eateries_shops/",
      "score": 1,
      "comments": 10,
      "post_id": "t3_1mv8gup",
      "post_type": "text",
      "domain": "self.penang",
      "author": "moonchilding",
      "author_id": "t2_fd5fwioe",
      "subreddit_id": "t5_2snuj",
      "subreddit": "r/penang",
      "created_ts": "2025-08-20T07:50:04.067000+0000",
      "content_href": "https://www.reddit.com/r/penang/comments/1mv8gup/sightseeingtourist_attractions_eateries_shops/",
      "content_preview": "",
      "flair": [
        "Discussion"
      ],
      "thumbnail_url": ""
    },
    {
      "title": "Where to get a 3D print or metal \"business card\" made?",
      "permalink": "https://www.reddit.com/r/penang/comments/1mub3xz/where_to_get_a_3d_print_or_metal_business_card/",
      "score": 3,
      "comments": 8,
      "post_id": "t3_1mub3xz",
      "post_type": "text",
      "domain": "self.penang",
      "author": "Panda_Blue-88",
      "author_id": "t2_4xjlhbf3",
      "subreddit_id": "t5_2snuj",
      "subreddit": "r/penang",
      "created_ts": "2025-08-19T06:50:49.443000+0000",
      "content_href": "https://www.reddit.com/r/penang/comments/1mub3xz/where_to_get_a_3d_print_or_metal_business_card/",
      "content_preview": "",
      "flair": [
        "Discussion"
      ],
      "thumbnail_url": ""
    },
    {
      "title": "Humidity in Penang?",
      "permalink": "https://www.reddit.com/r/penang/comments/1mu7a94/humidity_in_penang/",
      "score": 1,
      "comments": 24,
      "post_id": "t3_1mu7a94",
      "post_type": "text",
      "domain": "self.penang",
      "author": "Psychological-Way85",
      "author_id": "t2_1vlyuukoh1",
      "subreddit_id": "t5_2snuj",
      "subreddit": "r/penang",
      "created_ts": "2025-08-19T03:19:13.745000+0000",
      "content_href": "https://www.reddit.com/r/penang/comments/1mu7a94/humidity_in_penang/",
      "content_preview": "",
      "flair": [
        "Discussion"
      ],
      "thumbnail_url": "https://www.redditstatic.com/avatars/defaults/v2/avatar_default_5.png"
    },
    {
      "title": "Quick 2-Day Solo Trip to Penang - Need some practical advice on food, sights & payment",
      "permalink": "https://www.reddit.com/r/penang/comments/1mtwmcq/quick_2day_solo_trip_to_penang_need_some/",
      "score": 3,
      "comments": 11,
      "post_id": "t3_1mtwmcq",
      "post_type": "text",
      "domain": "self.penang",
      "author": "peggyPPpeggy",
      "author_id": "t2_lal2ctz8",
      "subreddit_id": "t5_2snuj",
      "subreddit": "r/penang",
      "created_ts": "2025-08-18T19:55:10.330000+0000",
      "content_href": "https://www.reddit.com/r/penang/comments/1mtwmcq/quick_2day_solo_trip_to_penang_need_some/",
      "content_preview": "",
      "flair": [
        "Discussion"
      ],
      "thumbnail_url": "https://www.redditstatic.com/avatars/defaults/v2/avatar_default_4.png"
    },
    {
      "title": "Taco Tuesday @ La Chica?",
      "permalink": "https://www.reddit.com/r/penang/comments/1mtdnfo/taco_tuesday_la_chica/",
      "score": 6,
      "comments": 3,
      "post_id": "t3_1mtdnfo",
      "post_type": "multi_media",
      "domain": "self.penang",
      "author": "ryViajero",
      "author_id": "t2_etdk4pal",
      "subreddit_id": "t5_2snuj",
      "subreddit": "r/penang",
      "created_ts": "2025-08-18T05:47:27.172000+0000",
      "content_href": "https://www.reddit.com/r/penang/comments/1mtdnfo/taco_tuesday_la_chica/",
      "content_preview": "",
      "flair": [
        "Discussion"
      ],
      "thumbnail_url": "https://www.redditstatic.com/avatars/defaults/v2/avatar_default_5.png"
    },
    {
      "title": "Can we settle this once and for all: Best hidden Char Koay Teow in Penang that’s NOT famous?",
      "permalink": "https://www.reddit.com/r/penang/comments/1mtec5k/can_we_settle_this_once_and_for_all_best_hidden/",
      "score": 4,
      "comments": 26,
      "post_id": "t3_1mtec5k",
      "post_type": "text",
      "domain": "self.penang",
      "author": "MidValleyGhost",
      "author_id": "t2_1s33lolayl",
      "subreddit_id": "t5_2snuj",
      "subreddit": "r/penang",
      "created_ts": "2025-08-18T06:28:06.392000+0000",
      "content_href": "https://www.reddit.com/r/penang/comments/1mtec5k/can_we_settle_this_once_and_for_all_best_hidden/",
      "content_preview": "",
      "flair": [
        "Discussion"
      ],
      "thumbnail_url": ""
    },
    {
      "title": "Platform Shoes/Boots/Heels",
      "permalink": "https://www.reddit.com/r/penang/comments/1mtfiy3/platform_shoesbootsheels/",
      "score": 1,
      "comments": 0,
      "post_id": "t3_1mtfiy3",
      "post_type": "image",
      "domain": "i.redd.it",
      "author": "Lazybumpanda",
      "author_id": "t2_comxb4uv5",
      "subreddit_id": "t5_2snuj",
      "subreddit": "r/penang",
      "created_ts": "2025-08-18T07:41:35.679000+0000",
      "content_href": "https://i.redd.it/cj08hpjefqjf1.jpeg",
      "content_preview": "",
      "flair": [
        "Picture"
      ],
      "thumbnail_url": "https://styles.redditmedia.com/t5_8iv7wz/styles/profileIcon_vjmmbfh3iiwe1.jpg?width=64&height=64&frame=1&auto=webp&crop=64%3A64%2Csmart&s=d0ceb42f5dcd6cdf275dd5fd0e8d3907798a5285"
    },
    {
      "title": "Where to buy?",
      "permalink": "https://www.reddit.com/r/penang/comments/1mtas6k/where_to_buy/",
      "score": 0,
      "comments": 9,
      "post_id": "t3_1mtas6k",
      "post_type": "gallery",
      "domain": "reddit.com",
      "author": "GroundbreakingTwo698",
      "author_id": "t2_ds0yzz90",
      "subreddit_id": "t5_2snuj",
      "subreddit": "r/penang",
      "created_ts": "2025-08-18T03:12:25.374000+0000",
      "content_href": "https://www.reddit.com/gallery/1mtas6k",
      "content_preview": "",
      "flair": [],
      "thumbnail_url": "https://preview.redd.it/where-to-buy-v0-08cppsdc3pjf1.jpg?width=640&crop=smart&auto=webp&s=ca02d3fb07e237e39c433b8bce616ec0b9a2d8fc"
    },
    {
      "title": "What sticker is this?",
      "permalink": "https://www.reddit.com/r/penang/comments/1msk28b/what_sticker_is_this/",
      "score": 41,
      "comments": 10,
      "post_id": "t3_1msk28b",
      "post_type": "image",
      "domain": "i.redd.it",
      "author": "yan5619",
      "author_id": "t2_3wfbk6dd",
      "subreddit_id": "t5_2snuj",
      "subreddit": "r/penang",
      "created_ts": "2025-08-17T06:58:00.350000+0000",
      "content_href": "https://i.redd.it/zyg4w8up2jjf1.jpeg",
      "content_preview": "",
      "flair": [
        "Picture"
      ],
      "thumbnail_url": "https://www.redditstatic.com/avatars/defaults/v2/avatar_default_1.png"
    },
    {
      "title": "EB80 Rapid Penang fare",
      "permalink": "https://www.reddit.com/r/penang/comments/1mtaf57/eb80_rapid_penang_fare/",
      "score": 1,
      "comments": 1,
      "post_id": "t3_1mtaf57",
      "post_type": "text",
      "domain": "self.penang",
      "author": "xordy",
      "author_id": "t2_ewkny",
      "subreddit_id": "t5_2snuj",
      "subreddit": "r/penang",
      "created_ts": "2025-08-18T02:54:52.495000+0000",
      "content_href": "https://www.reddit.com/r/penang/comments/1mtaf57/eb80_rapid_penang_fare/",
      "content_preview": "",
      "flair": [
        "Discussion"
      ],
      "thumbnail_url": ""
    },
    {
      "title": "Seang Pyn / Siang Pin Restaurant",
      "permalink": "https://www.reddit.com/r/penang/comments/1mshw7m/seang_pyn_siang_pin_restaurant/",
      "score": 1,
      "comments": 8,
      "post_id": "t3_1mshw7m",
      "post_type": "multi_media",
      "domain": "self.penang",
      "author": "magnomagna",
      "author_id": "t2_3952v80x",
      "subreddit_id": "t5_2snuj",
      "subreddit": "r/penang",
      "created_ts": "2025-08-17T04:52:56.163000+0000",
      "content_href": "https://www.reddit.com/r/penang/comments/1mshw7m/seang_pyn_siang_pin_restaurant/",
      "content_preview": "",
      "flair": [
        "Discussion"
      ],
      "thumbnail_url": ""
    },
    {
      "title": "Live in Sarwak and Tour KL/Penang OR Live in KL or Penang?",
      "permalink": "https://www.reddit.com/r/penang/comments/1ms1pn6/live_in_sarwak_and_tour_klpenang_or_live_in_kl_or/",
      "score": 1,
      "comments": 8,
      "post_id": "t3_1ms1pn6",
      "post_type": "text",
      "domain": "self.penang",
      "author": "Psychological-Way85",
      "author_id": "t2_1vlyuukoh1",
      "subreddit_id": "t5_2snuj",
      "subreddit": "r/penang",
      "created_ts": "2025-08-16T17:25:32.337000+0000",
      "content_href": "https://www.reddit.com/r/penang/comments/1ms1pn6/live_in_sarwak_and_tour_klpenang_or_live_in_kl_or/",
      "content_preview": "",
      "flair": [
        "Discussion"
      ],
      "thumbnail_url": "https://www.redditstatic.com/avatars/defaults/v2/avatar_default_5.png"
    },
    {
      "title": "Cafe Recommendations",
      "permalink": "https://www.reddit.com/r/penang/comments/1mrq9g5/cafe_recommendations/",
      "score": 1,
      "comments": 2,
      "post_id": "t3_1mrq9g5",
      "post_type": "text",
      "domain": "self.penang",
      "author": "juanritos",
      "author_id": "t2_12rc4b",
      "subreddit_id": "t5_2snuj",
      "subreddit": "r/penang",
      "created_ts": "2025-08-16T09:27:37.155000+0000",
      "content_href": "https://www.reddit.com/r/penang/comments/1mrq9g5/cafe_recommendations/",
      "content_preview": "",
      "flair": [
        "Discussion"
      ],
      "thumbnail_url": ""
    },
    {
      "title": "Meeting people",
      "permalink": "https://www.reddit.com/r/penang/comments/1mr15af/meeting_people/",
      "score": 6,
      "comments": 15,
      "post_id": "t3_1mr15af",
      "post_type": "text",
      "domain": "self.penang",
      "author": "Wizard--Robot",
      "author_id": "t2_f0lvd94s",
      "subreddit_id": "t5_2snuj",
      "subreddit": "r/penang",
      "created_ts": "2025-08-15T15:29:35.659000+0000",
      "content_href": "https://www.reddit.com/r/penang/comments/1mr15af/meeting_people/",
      "content_preview": "",
      "flair": [
        "Discussion"
      ],
      "thumbnail_url": "https://www.redditstatic.com/avatars/defaults/v2/avatar_default_4.png"
    },
    {
      "title": "Salary negotiation",
      "permalink": "https://www.reddit.com/r/penang/comments/1mqqgdn/salary_negotiation/",
      "score": 4,
      "comments": 19,
      "post_id": "t3_1mqqgdn",
      "post_type": "text",
      "domain": "self.penang",
      "author": "rixxxy100",
      "author_id": "t2_p25k3",
      "subreddit_id": "t5_2snuj",
      "subreddit": "r/penang",
      "created_ts": "2025-08-15T07:13:48.843000+0000",
      "content_href": "https://www.reddit.com/r/penang/comments/1mqqgdn/salary_negotiation/",
      "content_preview": "",
      "flair": [
        "Discussion"
      ],
      "thumbnail_url": ""
    },
    {
      "title": "Which weather app to use in Penang?",
      "permalink": "https://www.reddit.com/r/penang/comments/1mqnuyu/which_weather_app_to_use_in_penang/",
      "score": 6,
      "comments": 8,
      "post_id": "t3_1mqnuyu",
      "post_type": "text",
      "domain": "self.penang",
      "author": "m0smorde",
      "author_id": "t2_da3sz0y74",
      "subreddit_id": "t5_2snuj",
      "subreddit": "r/penang",
      "created_ts": "2025-08-15T04:49:33.357000+0000",
      "content_href": "https://www.reddit.com/r/penang/comments/1mqnuyu/which_weather_app_to_use_in_penang/",
      "content_preview": "",
      "flair": [
        "Discussion"
      ],
      "thumbnail_url": ""
    },
    {
      "title": "Do you know of sports massage? *A survey*",
      "permalink": "https://www.reddit.com/r/penang/comments/1mpxy87/do_you_know_of_sports_massage_a_survey/",
      "score": 3,
      "comments": 1,
      "post_id": "t3_1mpxy87",
      "post_type": "text",
      "domain": "self.penang",
      "author": "redverd",
      "author_id": "t2_15uqq7",
      "subreddit_id": "t5_2snuj",
      "subreddit": "r/penang",
      "created_ts": "2025-08-14T11:28:14.618000+0000",
      "content_href": "https://www.reddit.com/r/penang/comments/1mpxy87/do_you_know_of_sports_massage_a_survey/",
      "content_preview": "",
      "flair": [
        "Discussion"
      ],
      "thumbnail_url": ""
    },
    {
      "title": "Penang clients are cheapskate, no standard",
      "permalink": "https://www.reddit.com/r/penang/comments/1mpog4y/penang_clients_are_cheapskate_no_standard/",
      "score": 3,
      "comments": 28,
      "post_id": "t3_1mpog4y",
      "post_type": "text",
      "domain": "self.penang",
      "author": "TrueButterscotch2840",
      "author_id": "t2_kur7lmk3v",
      "subreddit_id": "t5_2snuj",
      "subreddit": "r/penang",
      "created_ts": "2025-08-14T02:37:38.536000+0000",
      "content_href": "https://www.reddit.com/r/penang/comments/1mpog4y/penang_clients_are_cheapskate_no_standard/",
      "content_preview": "",
      "flair": [
        "Discussion"
      ],
      "thumbnail_url": ""
    },
    {
      "title": "Views from the top of Penang Hill.",
      "permalink": "https://www.reddit.com/r/penang/comments/1movqsx/views_from_the_top_of_penang_hill/",
      "score": 54,
      "comments": 1,
      "post_id": "t3_1movqsx",
      "post_type": "gallery",
      "domain": "reddit.com",
      "author": "MidValleyGhost",
      "author_id": "t2_1s33lolayl",
      "subreddit_id": "t5_2snuj",
      "subreddit": "r/penang",
      "created_ts": "2025-08-13T05:17:30.230000+0000",
      "content_href": "https://www.reddit.com/gallery/1movqsx",
      "content_preview": "",
      "flair": [],
      "thumbnail_url": "https://preview.redd.it/views-from-the-top-of-penang-hill-v0-ucnky8p41qif1.jpg?width=640&crop=smart&auto=webp&s=128885654b67c29ec9c1f4af88f11789022fca2a"
    },
    {
      "title": "seen on wplace",
      "permalink": "https://www.reddit.com/r/penang/comments/1mp5un1/seen_on_wplace/",
      "score": 5,
      "comments": 0,
      "post_id": "t3_1mp5un1",
      "post_type": "multi_media",
      "domain": "self.penang",
      "author": "Dogecraft27",
      "author_id": "t2_xchea",
      "subreddit_id": "t5_2snuj",
      "subreddit": "r/penang",
      "created_ts": "2025-08-13T14:22:24.118000+0000",
      "content_href": "https://www.reddit.com/r/penang/comments/1mp5un1/seen_on_wplace/",
      "content_preview": "",
      "flair": [
        "Discussion"
      ],
      "thumbnail_url": "https://www.redditstatic.com/avatars/defaults/v2/avatar_default_2.png"
    },
    {
      "title": "How do you explain Penang to foreign friends without sounding like a tour guide?",
      "permalink": "https://www.reddit.com/r/penang/comments/1mn5lpt/how_do_you_explain_penang_to_foreign_friends/",
      "score": 14,
      "comments": 16,
      "post_id": "t3_1mn5lpt",
      "post_type": "text",
      "domain": "self.penang",
      "author": "MidValleyGhost",
      "author_id": "t2_1s33lolayl",
      "subreddit_id": "t5_2snuj",
      "subreddit": "r/penang",
      "created_ts": "2025-08-11T06:28:09.934000+0000",
      "content_href": "https://www.reddit.com/r/penang/comments/1mn5lpt/how_do_you_explain_penang_to_foreign_friends/",
      "content_preview": "",
      "flair": [
        "Discussion"
      ],
      "thumbnail_url": ""
    }
  ],
  "scraped_at": "2025-09-02T12:53:51.681735"
}